auditrin/__init__.py
auditrin/audit.py
auditrin/cli.py
auditrin-0.1.0.dist-info/METADATA
auditrin-0.1.0.dist-info/WHEEL
auditrin-0.1.0.dist-info/entry_points.txt
auditrin-0.1.0.dist-info/licenses/LICENSE
auditrin-0.1.0.dist-info/RECORD
