Metadata-Version: 2.4
Name: auditrin
Version: 0.1.0
Summary: AI-powered documentation drift detection - Ensure your docs stay in sync with your code
Project-URL: Homepage, https://github.com/SecrinLabs/secrin
Project-URL: Documentation, https://github.com/SecrinLabs/secrin/tree/main/packages/auditor
Project-URL: Repository, https://github.com/SecrinLabs/secrin
Project-URL: Issues, https://github.com/SecrinLabs/secrin/issues
Author-email: Secrin Labs <hello@secrinlabs.com>
License-Expression: MIT
License-File: LICENSE
Keywords: ai,audit,cli,developer-tools,docs-as-code,documentation,drift-detection,gemini
Classifier: Development Status :: 4 - Beta
Classifier: Environment :: Console
Classifier: Intended Audience :: Developers
Classifier: License :: OSI Approved :: MIT License
Classifier: Operating System :: OS Independent
Classifier: Programming Language :: Python :: 3
Classifier: Programming Language :: Python :: 3.11
Classifier: Programming Language :: Python :: 3.12
Classifier: Topic :: Documentation
Classifier: Topic :: Software Development :: Documentation
Classifier: Topic :: Software Development :: Quality Assurance
Requires-Python: >=3.11
Requires-Dist: click>=8.1.0
Requires-Dist: google-genai>=1.0.0
Requires-Dist: rich>=13.0.0
